coffeeblack/__init__.py
coffeeblack/core.py
coffeeblack/extract.py
coffeeblack/tasks.py
coffeeblack/types.py
coffeeblack/utils/__init__.py
coffeeblack/utils/app_manager.py
coffeeblack/utils/debug.py
coffeeblack/utils/screenshot.py
coffeeblack/utils/window.py
coffeeblack-0.1.12.dist-info/LICENSE
coffeeblack-0.1.12.dist-info/METADATA
coffeeblack-0.1.12.dist-info/WHEEL
coffeeblack-0.1.12.dist-info/top_level.txt
coffeeblack-0.1.12.dist-info/RECORD
