Metadata-Version: 2.1
Name: coffeeblack
Version: 0.1.12
Summary: Python client for interacting with the CoffeeBlack visual reasoning API
Home-page: https://github.com/coffeeblack/sdk
Author: CoffeeBlack AI
Author-email: info@coffeeblack.ai
Classifier: Programming Language :: Python :: 3
Classifier: License :: OSI Approved :: MIT License
Classifier: Operating System :: OS Independent
Requires-Python: >=3.7
License-File: LICENSE
Requires-Dist: pyautogui
Requires-Dist: aiohttp
Requires-Dist: asyncio
Requires-Dist: pillow
Requires-Dist: numpy
Requires-Dist: opencv-python
Requires-Dist: mss
